c2w/__init__.py
c2w/c2w.py
c2w-0.0.1.dist-info/LICENSE
c2w-0.0.1.dist-info/METADATA
c2w-0.0.1.dist-info/WHEEL
c2w-0.0.1.dist-info/entry_points.txt
c2w-0.0.1.dist-info/top_level.txt
c2w-0.0.1.dist-info/RECORD
