Metadata-Version: 2.1
Name: c2w
Version: 0.0.1
Summary: convert CLI programs to web services
Home-page: https://github.com/dongyx/c2w
Author: DONG Yuxuan
Author-email: dong_yuxuan@icloud.com
License: MIT
Platform: UNKNOWN
Classifier: Programming Language :: Python :: 3
Classifier: License :: OSI Approved :: MIT License
Requires-Python: >=3.6
